lcutil/__init__.py
lcutil/find_between.py
lcutil/imap_tool.py
lcutil/util.py
lcutil/util_db.py
lcutil/util_email.py
lcutil/util_fs.py
lcutil/util_ftp.py
lcutil/util_image.py
lcutil/util_logging.py
lcutil-0.2.2.dist-info/LICENSE
lcutil-0.2.2.dist-info/METADATA
lcutil-0.2.2.dist-info/WHEEL
lcutil-0.2.2.dist-info/entry_points.txt
lcutil-0.2.2.dist-info/top_level.txt
lcutil-0.2.2.dist-info/RECORD
