Metadata-Version: 2.1
Name: lcutil
Version: 0.2.2
Summary: General useful utility functions for Python projects.
Home-page: http://github.com/lcordier/lcutil/
Author: Louis Cordier
Author-email: lcordier@gmail.com
License: MIT
Keywords: utility functions devel
Platform: UNKNOWN
Classifier: Development Status :: 4 - Beta
Classifier: Intended Audience :: Developers
Classifier: License :: OSI Approved :: MIT License
Classifier: Programming Language :: Python :: 2.7
Classifier: Topic :: Software Development
Requires-Dist: imapclient
Requires-Dist: pyzmail
Requires-Dist: unidecode
Requires-Dist: ftputil
Requires-Dist: paramiko
Requires-Dist: pillow
Requires-Dist: logging-tree
